co_eco/__init__.py
co_eco/core.py
co_eco/critical_values.py
co_eco/results.py
co_eco/utils.py
co_eco/data/Lbar01n.txt
co_eco/data/Lbar02n.txt
co_eco/data/Lbar11n.txt
co_eco/data/Lbar12n.txt
co_eco/data/Lbar21n.txt
co_eco/data/Lbar22n.txt
co_eco/data/USbudget.txt
co_eco/data/__init__.py
co_eco-0.0.1.dist-info/licenses/LICENSE
co_eco-0.0.1.dist-info/METADATA
co_eco-0.0.1.dist-info/WHEEL
co_eco-0.0.1.dist-info/top_level.txt
co_eco-0.0.1.dist-info/RECORD
